.installed.cfg
.mr.developer.cfg
.travis.yml
MANIFEST.in
Makefile
README.rst
bootstrap.py
buildout.cfg
setup.py
buildout.d/base.cfg
buildout.d/development.cfg
buildout.d/versions.cfg
docs/CHANGELOG.rst
docs/LICENSE.rst
src/niteoweb/__init__.py
src/niteoweb/__init__.pyc
src/niteoweb.ipn.jvzoo.egg-info/PKG-INFO
src/niteoweb.ipn.jvzoo.egg-info/SOURCES.txt
src/niteoweb.ipn.jvzoo.egg-info/dependency_links.txt
src/niteoweb.ipn.jvzoo.egg-info/entry_points.txt
src/niteoweb.ipn.jvzoo.egg-info/namespace_packages.txt
src/niteoweb.ipn.jvzoo.egg-info/not-zip-safe
src/niteoweb.ipn.jvzoo.egg-info/requires.txt
src/niteoweb.ipn.jvzoo.egg-info/top_level.txt
src/niteoweb/ipn/__init__.py
src/niteoweb/ipn/__init__.pyc
src/niteoweb/ipn/jvzoo/__init__.py
src/niteoweb/ipn/jvzoo/__init__.pyc
src/niteoweb/ipn/jvzoo/configure.zcml
src/niteoweb/ipn/jvzoo/interfaces.py
src/niteoweb/ipn/jvzoo/interfaces.pyc
src/niteoweb/ipn/jvzoo/jvzoo.py
src/niteoweb/ipn/jvzoo/jvzoo.pyc
src/niteoweb/ipn/jvzoo/testing.py
src/niteoweb/ipn/jvzoo/testing.pyc
src/niteoweb/ipn/jvzoo/profiles/default/memberdata_properties.xml
src/niteoweb/ipn/jvzoo/profiles/default/metadata.xml
src/niteoweb/ipn/jvzoo/profiles/default/registry.xml
src/niteoweb/ipn/jvzoo/tests/__init__.py
src/niteoweb/ipn/jvzoo/tests/__init__.pyc
src/niteoweb/ipn/jvzoo/tests/test_jvzoo.py
src/niteoweb/ipn/jvzoo/tests/test_jvzoo.pyc
src/niteoweb/ipn/jvzoo/tests/test_setup.py
src/niteoweb/ipn/jvzoo/tests/test_setup.pyc
src/niteoweb/ipn/jvzoo/upgrades/__init__.py
src/niteoweb/ipn/jvzoo/upgrades/__init__.pyc
src/niteoweb/ipn/jvzoo/upgrades/configure.zcml
src/niteoweb/ipn/jvzoo/upgrades/upgrades.py
src/niteoweb/ipn/jvzoo/upgrades/upgrades.pyc