Metadata-Version: 1.1
Name: niteoweb.ipn.jvzoo
Version: 1.5
Summary: JVZoo IPN support in Plone.
Home-page: http://pypi.python.org/pypi/niteoweb.ipn.jvzoo
Author: NiteoWeb Ltd.
Author-email: info@niteoweb.com
License: BSD
Keywords: Plone IPN JVZoo
Platform: UNKNOWN
Classifier: Framework :: Plone
Classifier: Programming Language :: Python
